poetry_learn/__init__.py
poetry_learn/main.py
poetry_learn_publish-0.1.0.dist-info/METADATA
poetry_learn_publish-0.1.0.dist-info/WHEEL
poetry_learn_publish-0.1.0.dist-info/entry_points.txt
poetry_learn_publish-0.1.0.dist-info/RECORD
