Metadata-Version: 2.3
Name: poetry-learn-publish
Version: 0.1.0
Summary: 
Author: Nayabrasul Shaik
Author-email: rasulnrasul@gmail.com
Requires-Python: >=3.12
Classifier: Programming Language :: Python :: 3
Classifier: Programming Language :: Python :: 3.12
Classifier: Programming Language :: Python :: 3.13
Requires-Dist: pybullet (>=3.2.7,<4.0.0)
